rheos_common/__init__.py
rheos_common/model/__init__.py
rheos_common/model/locus.py
rheos_common/model/partitioner.py
rheos_common/model/read_pair.py
rheos_common/model/variant_candidate.py
rheos_common/model/variant_candidate_collection.py
rheos_common/util/__init__.py
rheos_common/util/common.py
rheos_common/util/logging.py
rheos_common-0.0.7.dist-info/METADATA
rheos_common-0.0.7.dist-info/WHEEL
rheos_common-0.0.7.dist-info/top_level.txt
rheos_common-0.0.7.dist-info/RECORD
