Metadata-Version: 2.1
Name: rheos-common
Version: 0.0.7
Summary: Classes common to various Rheos tools
Home-page: https://github.com/llevar/rheos
Author: Sergei Yakneen
Author-email: llevar@gmail.com
License: UNKNOWN
Platform: UNKNOWN
Classifier: Programming Language :: Python :: 3
Classifier: License :: OSI Approved :: MIT License
Classifier: Operating System :: OS Independent
Requires-Dist: sortedcontainers (>=2.1.0)
